trainloop/__init__.py
trainloop/hooks.py
trainloop/py.typed
trainloop/trainer.py
trainloop/utils.py
trainloop-0.1.0.dist-info/WHEEL
trainloop-0.1.0.dist-info/METADATA
trainloop-0.1.0.dist-info/RECORD
