Metadata-Version: 2.3
Name: trainloop
Version: 0.1.0
Summary: Minimal PyTorch training loop with hooks and checkpointing.
Author: Karim Abou Zeid
Author-email: Karim Abou Zeid <contact@ka.codes>
Requires-Dist: pillow>=11.3.0
Requires-Dist: torch>=2.0.0
Requires-Python: >=3.10
